{
    "type": "Collection",
    "label": {
        "sv": [
            "Bergväsen"
        ]
    },
    "summary": {
        "sv": [
            "Bergväsen"
        ]
    },
    "items": [
        {
            "id": "{host}collection/arkiv/SBj6bDX9rH6cxG02H087k3",
            "type": "Collection",
            "label": {
                "sv": [
                    "Bergmästaren i Nora m fl bergslag"
				]
            }
        },
        {
            "id": "{host}collection/arkiv/SRj6bDX9rH6cxG02H087k3",
            "type": "Collection",
            "label": {
                "sv": [
                    "Bergmästaren i Nya Kopparbergs m fl bergslag"
				]
            }
        },
        {
            "id": "{host}collection/arkiv/WRjnDmy6OoJE9IBY9FEr77",
            "type": "Collection",
            "label": {
                "sv": [
                    "Bergmästarens i norra distriktet arkiv"
				]
            }
        },
        {
            "id": "{host}collection/arkiv/9ZzBq5lDQeZJW0018W43t3",
            "type": "Collection",
            "label": {
                "sv": [
                    "Bergsbyrån. Gruvkartekontoret"
				]
            }
        },
        {
            "id": "{host}collection/arkiv/v19jJwVer16xnm3GjpvwY3",
            "type": "Collection",
            "label": {
                "sv": [
                    "8:e bergmästaredistriktet arkiv - Diarier över avgångna skrivelser m.m., allmän serie"
				]
            }
        },
        {
            "id": "{host}collection/arkiv/un9jJwVer16xnm3GjpvwY3",
            "type": "Collection",
            "label": {
                "sv": [
                    "8:e bergmästaredistriktet arkiv - Diarier över inkomna skrivelser m.m., allmän serie"
				]
            }
        },
        {
            "id": "{host}collection/arkiv/vX9jJwVer16xnm3GjpvwY3",
            "type": "Collection",
            "label": {
                "sv": [
                    "8:e bergmästaredistriktet arkiv - Liggare och förteckningar över utfärdade mutsedlar (tillståndsbevis), vilostånd och utmål"
				]
            }
        },
        {
            "id": "{host}collection/arkiv/Dothbq6tb4EriYvj700qK3",
            "type": "Collection",
            "label": {
                "sv": [
                    "Bergsjordeböcker"
				]
            }
        }
	]
}