{
    "type": "Collection",
    "label": {
        "sv": [
            "Fotografier"
        ],
        "en": [
            "Photographies"
        ]
    },
    "summary": {
        "sv": [
            "Arkivenheter sorterade efter ämnesområde: fotografier"
        ],
        "en": [
            "Archival records sorted by subject: photographies"
        ]
    },
    "items": [
        {
            "id": "{host}collection/arkiv/hbHhUFT8rH6cxG02H087k3",
            "type": "Collection",
            "label": {
                "sv": [
                    "Bobergska släktarkivet, Undersåker 1804–1893"
                ]
            }
        },
        {
            "id": "{host}collection/arkiv/zPlRpz2tOfBfVqt04HBZLD",
            "type": "Collection",
            "label": {
                "sv": [
                    "Huldtska släktarkivet, fotografisamling"
                ]
            }
        },
        {
            "id": "{host}collection/arkiv/B5HhUFT8rH6cxG02H087k3",
            "type": "Collection",
            "label": {
                "sv": [
                    "Janrik Bromés samling"
                ]
            }
        },
        {
            "id": "{host}collection/arkiv/lqu9MdBfoKQXmoyUvFWtb2",
            "type": "Collection",
            "label": {
                "sv": [
                    "Kalls sockenarkiv"
                ]
            }
        },
        {
            "id": "{host}collection/arkiv/BZc5BXD6rH6cxG02H087k3",
            "type": "Collection",
            "label": {
                "sv": [
                    "Landshövding Carl Gustaf Lagercrantzs arkiv"
                ]
            }
        },
        {
            "id": "{host}collection/arkiv/gJc5BXD6rH6cxG02H087k3",
            "type": "Collection",
            "label": {
                "sv": [
                    "Paul Wagenius arkiv"
                ]
            }
        },
        {
            "id": "{host}collection/fotografier-militart",
            "type": "Collection",
            "label": {
                "sv": [
                    "Fotografier - militärt"
                ]
            }
        }
	]
}